discord_user_api/__init__.py
user_discord_api-0.0.1.dist-info/METADATA
user_discord_api-0.0.1.dist-info/WHEEL
user_discord_api-0.0.1.dist-info/top_level.txt
user_discord_api-0.0.1.dist-info/RECORD
